Workbook

Sheet Sheet1
B1: portfolio tracker
B2: last update | C2: =TODAY() -> 46175
C4: Ticker | D4: name | E4: shares | F4: cost basis | G4: current price | H4: market value | I4: total cost | J4: G/L | K4: % | L4: weight
B5: STOCKS
B6: {=_FV(C6,"Ticker symbol",TRUE)} -> NVDA | C6: #VALUE! | D6: {=_FV(C6,"Name")} -> NVIDIA CORPORATION | E6: 3.447619 | F6: 45 | G6: {=_FV(C6,"Price")} -> 222.86 | H6: =G6*E6 -> 768.33638 | I6: =F6*E6 -> 155.14286 | J6: =H6-I6 -> 613.19352 | K6: =H6/I6-1 -> 3.9524444 | L6: =H6/$H$29 -> 0.011214253
B7: {=_FV(C7,"Ticker symbol",TRUE)} -> AAPL | C7: #VALUE! | D7: {=_FV(C7,"Name")} -> APPLE INC. | E7: 3.7904762 | F7: 500 | G7: {=_FV(C7,"Price")} -> 314.75 | H7: =G7*E7 -> 1193.0524 | I7: =F7*E7 -> 1895.2381 | J7: =H7-I7 -> -702.18571 | K7: =H7/I7-1 -> -0.3705 | L7: =H7/$H$29 -> 0.017413195
B8: {=_FV(C8,"Ticker symbol",TRUE)} -> MSFT | C8: #VALUE! | D8: {=_FV(C8,"Name")} -> MICROSOFT CORPORATION | E8: 4.1333333 | F8: 340 | G8: {=_FV(C8,"Price")} -> 441.89 | H8: =G8*E8 -> 1826.4787 | I8: =F8*E8 -> 1405.3333 | J8: =H8-I8 -> 421.14533 | K8: =H8/I8-1 -> 0.29967647 | L8: =H8/$H$29 -> 0.026658367
B9: {=_FV(C9,"Ticker symbol",TRUE)} -> GOOGL | C9: #VALUE! | D9: {=_FV(C9,"Name")} -> ALPHABET INC. | E9: 4.4761905 | F9: 565 | G9: {=_FV(C9,"Price")} -> 363.94 | H9: =G9*E9 -> 1629.0648 | I9: =F9*E9 -> 2529.0476 | J9: =H9-I9 -> -899.98286 | K9: =H9/I9-1 -> -0.35585841 | L9: =H9/$H$29 -> 0.023777013
B10: {=_FV(C10,"Ticker symbol",TRUE)} -> KO | C10: #VALUE! | D10: {=_FV(C10,"Name")} -> THE COCA-COLA COMPANY | E10: 4.8190476 | F10: 34 | G10: {=_FV(C10,"Price")} -> 78.45 | H10: =G10*E10 -> 378.05429 | I10: =F10*E10 -> 163.84762 | J10: =H10-I10 -> 214.20667 | K10: =H10/I10-1 -> 1.3073529 | L10: =H10/$H$29 -> 0.0055178909
B11: {=_FV(C11,"Ticker symbol",TRUE)} -> PEP | C11: #VALUE! | D11: {=_FV(C11,"Name")} -> Pepsico, Inc. | E11: 5.1619048 | F11: 243 | G11: {=_FV(C11,"Price")} -> 142.25 | H11: =G11*E11 -> 734.28095 | I11: =F11*E11 -> 1254.3429 | J11: =H11-I11 -> -520.0619 | K11: =H11/I11-1 -> -0.41460905 | L11: =H11/$H$29 -> 0.010717197
B12: {=_FV(C12,"Ticker symbol",TRUE)} -> META | C12: #VALUE! | D12: {=_FV(C12,"Name")} -> META PLATFORMS, INC. | E12: 5.5047619 | F12: 35 | G12: {=_FV(C12,"Price")} -> 600.625 | H12: =G12*E12 -> 3306.2976 | I12: =F12*E12 -> 192.66667 | J12: =H12-I12 -> 3113.631 | K12: =H12/I12-1 -> 16.160714 | L12: =H12/$H$29 -> 0.048257063
B13: {=_FV(C13,"Ticker symbol",TRUE)} -> AMZN | C13: #VALUE! | D13: {=_FV(C13,"Name")} -> AMAZON.COM, INC. | E13: 5.847619 | F13: 982 | G13: {=_FV(C13,"Price")} -> 258.05 | H13: =G13*E13 -> 1508.9781 | I13: =F13*E13 -> 5742.3619 | J13: =H13-I13 -> -4233.3838 | K13: =H13/I13-1 -> -0.73721996 | L13: =H13/$H$29 -> 0.022024288
B14: {=_FV(C14,"Ticker symbol",TRUE)} -> WM | C14: #VALUE! | D14: {=_FV(C14,"Name")} -> WASTE MANAGEMENT, INC. | E14: 6.1904762 | F14: 12 | G14: {=_FV(C14,"Price")} -> 211.165 | H14: =G14*E14 -> 1307.2119 | I14: =F14*E14 -> 74.285714 | J14: =H14-I14 -> 1232.9262 | K14: =H14/I14-1 -> 16.597083 | L14: =H14/$H$29 -> 0.01907941
B15: {=_FV(C15,"Ticker symbol",TRUE)} -> HRL | C15: #VALUE! | D15: {=_FV(C15,"Name")} -> HORMEL FOODS CORPORATION | E15: 6.5333333 | F15: 542 | G15: {=_FV(C15,"Price")} -> 23.385 | H15: =G15*E15 -> 152.782 | I15: =F15*E15 -> 3541.0667 | J15: =H15-I15 -> -3388.2847 | K15: =H15/I15-1 -> -0.95685424 | L15: =H15/$H$29 -> 0.0022299295
B16: {=_FV(C16,"Ticker symbol",TRUE)} -> NKE | C16: #VALUE! | D16: {=_FV(C16,"Name")} -> NIKE, INC. | E16: 6.8761905 | F16: 146 | G16: {=_FV(C16,"Price")} -> 43.525 | H16: =G16*E16 -> 299.28619 | I16: =F16*E16 -> 1003.9238 | J16: =H16-I16 -> -704.63762 | K16: =H16/I16-1 -> -0.70188356 | L16: =H16/$H$29 -> 0.0043682313
B17: {=_FV(C17,"Ticker symbol",TRUE)} -> ASML | C17: #VALUE! | D17: {=_FV(C17,"Name")} -> ASML Holding NV | E17: 7.2190476 | F17: 2400 | G17: {=_FV(C17,"Price")} -> 1695.43 | H17: =G17*E17 -> 12239.39 | I17: =F17*E17 -> 17325.714 | J17: =H17-I17 -> -5086.3244 | K17: =H17/I17-1 -> -0.29357083 | L17: =H17/$H$29 -> 0.17864
... B20: {=_FV(C20,"Ticker symbol",TRUE)} -> ENB.PR.I | C20: #VALUE! | D20: {=_FV(C20,"Name")} -> Enbridge Inc. | E20: 8.247619 | F20: 432 | G20: {=_FV(C20,"Price")} -> 21.47 | H20: =G20*E20 -> 177.07638 | I20: =F20*E20 -> 3562.9714 | J20: =H20-I20 -> -3385.895 | K20: =H20/I20-1 -> -0.95030093 | L20: =H20/$H$29 -> 0.0025845181
B21: ETF'S
C22: #VALUE! | D22: {=_FV(C22,"Name")} -> Invesco QQQ Mega Fund | E22: 1 | F22: 1200 | G22: {=_FV(C22,"Price")} -> 14056 | H22: =G22*E22 -> 14056 | I22: =F22*E22 -> 1200 | J22: =H22-I22 -> 12856 | K22: =H22/I22-1 -> 10.713333 | L22: =H22/$H$29 -> 0.20515433
C23: #VALUE! | D23: {=_FV(C23,"Name")} -> Vanguard 500 Index Fund;Institutional Select | E23: 9 | F23: 345 | G23: {=_FV(C23,"Price")} -> 372.53 | H23: =G23*E23 -> 3352.77 | I23: =F23*E23 -> 3105 | J23: =H23-I23 -> 247.77 | K23: =H23/I23-1 -> 0.079797101 | L23: =H23/$H$29 -> 0.048935351
C24: #VALUE! | D24: {=_FV(C24,"Name")} -> State Street SPDR S&P500 | E24: 12 | F24: 222 | G24: {=_FV(C24,"Price")} -> 759.365 | H24: =G24*E24 -> 9112.38 | I24: =F24*E24 -> 2664 | J24: =H24-I24 -> 6448.38 | K24: =H24/I24-1 -> 2.4205631 | L24: =H24/$H$29 -> 0.13299973
B25: ALTERNATIVE
B26: GLD | C26: #VALUE! | D26: {=_FV(C26,"Name")} -> SPDR Gold | E26: 33 | F26: 123 | G26: {=_FV(C26,"Price")} -> 411.8201 | H26: =G26*E26 -> 13590.063 | I26: =F26*E26 -> 4059 | J26: =H26-I26 -> 9531.0633 | K26: =H26/I26-1 -> 2.3481309 | L26: =H26/$H$29 -> 0.19835375
B27: IBIT | C27: #VALUE! | D27: {=_FV(C27,"Name")} -> iShares Bitcoin Trust | E27: 23 | F27: 23 | G27: {=_FV(C27,"Price")} -> 38.055 | H27: =G27*E27 -> 875.265 | I27: =F27*E27 -> 529 | J27: =H27-I27 -> 346.265 | K27: =H27/I27-1 -> 0.65456522 | L27: =H27/$H$29 -> 0.012774929
B28: SLV | C28: #VALUE! | D28: {=_FV(C28,"Name")} -> Selvita SA | E28: 55 | F28: 56 | G28: {=_FV(C28,"Price")} -> 30.55 | H28: =G28*E28 -> 1680.25 | I28: =F28*E28 -> 3080 | J28: =H28-I28 -> -1399.75 | K28: =H28/I28-1 -> -0.45446429 | L28: =H28/$H$29 -> 0.024524087
B29: PORTFOLIO TOTAL | H29: =SUM(H6:H28) -> 68514.273 | I29: =SUM(I6:I28) -> 61651.038 | J29: =H29-I29 -> 6863.2352 | K29: =H29/I29-1 -> 0.11132392 | L29: =SUM(L6:L28) -> 1
B36: Portfolio summary | E36: Asset Class | F36: Value | G36: Allocation | I36: rank | J36: holding | K36: amounts
B37: TOT market value | C37: =H29 -> 68514.273 | E37: =B5 -> STOCKS | F37: =SUM( H6:H20) -> 25847.545 | G37: =F37/$F$40 -> 0.37725781 | I37: 1 | J37: =INDEX($D$6:$D$28,MATCH(LARGE($H$6:$H$28,I37),$H$6:$H$28,0)) -> Invesco QQQ Mega Fund | K37: =LARGE($H$6:$H$28,I37) -> 14056
B38: TOT cost | C38: =I29 -> 61651.038 | E38: =B21 -> ETF'S | F38: =SUM(H22:H24) -> 26521.15 | G38: =F38/$F$40 -> 0.38708942 | I38: 2 | J38: =INDEX($D$6:$D$28,MATCH(LARGE($H$6:$H$28,I38),$H$6:$H$28,0)) -> SPDR Gold | K38: =LARGE($H$6:$H$28,I38) -> 13590.063
B39: TOT gain/Loss | C39: =J29 -> 6863.2352 | E39: =B25 -> ALTERNATIVE | F39: =SUM(H26:H28) -> 16145.578 | G39: =F39/$F$40 -> 0.23565277 | I39: 3 | J39: =INDEX($D$6:$D$28,MATCH(LARGE($H$6:$H$28,I39),$H$6:$H$28,0)) -> ASML Holding NV | K39: =LARGE($H$6:$H$28,I39) -> 12239.39
B40: TOT return % | C40: =K29 -> 0.11132392 | E40: total | F40: =SUM(F37:F39) -> 68514.273 | G40: =SUM(G37:G39) -> 1 | I40: 4 | J40: =INDEX($D$6:$D$28,MATCH(LARGE($H$6:$H$28,I40),$H$6:$H$28,0)) -> State Street SPDR S&P500 | K40: =LARGE($H$6:$H$28,I40) -> 9112.38
B41: # of holdings | C41: =COUNT(E6:E29) -> 21 | I41: 5 | J41: =INDEX($D$6:$D$28,MATCH(LARGE($H$6:$H$28,I41),$H$6:$H$28,0)) -> Vanguard 500 Index Fund;Institutional Select | K41: =LARGE($H$6:$H$28,I41) -> 3352.77
B45: portfolio allocation | E45: Top 5 Holdings

Sheet Sheet2
C2: 36454
B3: =Sheet1!C6 -> #VALUE! | C3: {=_xlfn.STOCKHISTORY(Sheet1!B6,Sheet2!C2)} -> Date | D3: Close | F3: =Sheet1!G6 -> 222.86 | G3: =Sheet1!H6 -> 768.33638 | H3: =Sheet1!I6 -> 155.14286 | I3: =Sheet1!J6 -> 613.19352 | J3: =Sheet1!K6 -> 3.9524444 | K3: =Sheet1!L6 -> 0.011214253 | L3: =Sheet1!M6 -> 0 | M3: =Sheet1!N6 -> 0 | ... T3: =Sheet1!U6 -> 0
B4: =Sheet1!C7 -> #VALUE! | C4: 36454 | D4: 0.04388
B5: =Sheet1!C8 -> #VALUE! | C5: {=_xlfn.STOCKHISTORY(Sheet1!B8,Sheet2!C4)} -> Date | D5: Close
B6: =Sheet1!C9 -> #VALUE! | C6: 36454 | D6: 46.5313
B7: =Sheet1!C10 -> #VALUE!
B8: =Sheet1!C11 -> #VALUE!
B9: =Sheet1!C12 -> #VALUE!
B10: =Sheet1!C13 -> #VALUE!
B11: =Sheet1!C14 -> #VALUE!
B12: =Sheet1!C15 -> #VALUE!
B13: =Sheet1!C16 -> #VALUE!
B14: =Sheet1!C17 -> #VALUE!
B15: =Sheet1!C18 -> #VALUE!
B16: =Sheet1!C19 -> #VALUE!
B17: =Sheet1!C20 -> #VALUE!
